{
  "$schema": "https://schemas.coderef.com/improvements/v1",
  "schema_version": "1.0",
  "project": "coderef-core",
  "scope": "scanner",
  "counter": 52,
  "last_updated": "2026-04-21T21:40:00Z",
  "last_pruned": "2026-04-21",
  "archived": [
    "IMP-CORE-003",
    "IMP-CORE-004",
    "IMP-CORE-006",
    "IMP-CORE-009",
    "IMP-CORE-010",
    "IMP-CORE-011-012",
    "IMP-CORE-014",
    "IMP-CORE-015",
    "IMP-CORE-016",
    "IMP-CORE-017",
    "IMP-CORE-018",
    "IMP-CORE-019",
    "IMP-CORE-020",
    "IMP-CORE-021",
    "IMP-CORE-022",
    "IMP-CORE-023",
    "IMP-CORE-024",
    "IMP-CORE-025",
    "IMP-CORE-026",
    "IMP-CORE-027",
    "IMP-CORE-028",
    "IMP-CORE-029",
    "IMP-CORE-030",
    "IMP-CORE-031",
    "IMP-CORE-032",
    "IMP-CORE-033",
    "IMP-CORE-034",
    "IMP-CORE-039",
    "IMP-CORE-042",
    "IMP-CORE-044"
  ],
  "items": [
    {
      "id": "IMP-CORE-036",
      "title": "Migrate route-parsers.ts to modular framework plugins",
      "category": "architecture",
      "severity": "major",
      "status": "open",
      "logged": "2026-04-20",
      "body": "route-parsers.ts is 518 lines with parsers for 7 frameworks (Flask, FastAPI, Express, Next.js, SvelteKit, Nuxt, Remix). Adding new frameworks requires modifying this central file, violating open/closed principle. Migrate to plugin architecture: src/analyzer/route-parsers/{framework}/parser.ts with common interface.",
      "files": ["src/analyzer/route-parsers.ts:1-517"],
      "related": ["WO-API-ROUTE-DETECTION-001"]
    },
    {
      "id": "IMP-CORE-038",
      "title": "Extract scanner framework detection to configurable registry",
      "category": "architecture",
      "severity": "minor",
      "status": "done",
      "logged": "2026-04-20",
      "completed": "2026-04-21",
      "body": "COMPLETED: Created framework-registry.ts with FrameworkRegistry class. Implemented 7 framework detectors: nextjs, sveltekit, nuxt, remix, express, flask, fastapi. Refactored scanner.ts to use frameworkRegistry.detectAll() instead of hardcoded methods. Old processXxxRoute methods deprecated but kept for backward compatibility.",
      "files": ["src/scanner/framework-registry.ts", "src/scanner/register-frameworks.ts", "src/analyzer/frameworks/"],
      "related": ["IMP-CORE-036"]
    },
    {
      "id": "IMP-CORE-043",
      "title": "Add middleware and dependency injection mapping",
      "category": "code-quality",
      "severity": "minor",
      "status": "done",
      "logged": "2026-04-20",
      "completed": "2026-04-21",
      "body": "COMPLETED: Implemented MiddlewareMapping interface matching migration-config-schema.json structure. Added detection for Flask (@login_required, @require_auth, @limiter.limit, @cross_origin), Django (@login_required, @permission_required, @csrf_*), and Express (app.use(auth), rateLimit) middleware patterns. Each mapping includes target framework pattern, conversion notes, and autoConvertible flag. Migration guidance covers Flask→FastAPI, Django→FastAPI, Express→NestJS conversions.",
      "files": ["src/analyzer/middleware-detector.ts"],
      "related": ["WO-MIGRATION-VALIDATION-001", "IMP-CORE-010"]
    },
    {
      "id": "IMP-CORE-050",
      "title": "TODO comments in fuzzy-resolver need resolution",
      "category": "code-quality",
      "severity": "minor",
      "status": "done",
      "logged": "2026-04-21",
      "completed": "2026-04-21",
      "body": "COMPLETED: Implemented Jaro-Winkler name similarity, weighted path similarity (filename 40%, directory overlap 35%, extension 15%, depth 10%), and metadata-based signature similarity (async, exported, parameters, type). All 3 TODOs removed. FuzzyResolver production-ready.",
      "files": ["src/context/fuzzy-resolver.ts:133", "src/context/fuzzy-resolver.ts:147", "src/context/fuzzy-resolver.ts:168"]
    },
    {
      "id": "IMP-CORE-051",
      "title": "Registry has unresolved implementation notes",
      "category": "code-quality",
      "severity": "minor",
      "status": "done",
      "logged": "2026-04-21",
      "completed": "2026-04-21",
      "body": "CLOSED (INVALID): No TODO/FIXME comments found in entity-registry.ts. Comments at lines 30, 32 are implementation notes explaining UUID v5 bit manipulation, not unresolved work items. Code review confirms proper deduplication (line 51-53) and no cache invalidation edge cases exist.",
      "files": ["src/registry/entity-registry.ts"]
    }
  ],
  "_note": "1 open item after completing 038, 043, 050, 051. 039, 042, 044 also archived. Counter remains at 52. Last updated 2026-04-21."
}
